trouve/__init__.py
trouve/events.py
trouve/find_events.py
trouve/transformations.py
trouve-0.6.0.dist-info/LICENSE.txt
trouve-0.6.0.dist-info/METADATA
trouve-0.6.0.dist-info/WHEEL
trouve-0.6.0.dist-info/top_level.txt
trouve-0.6.0.dist-info/RECORD
