Metadata-Version: 2.1
Name: trouve
Version: 0.6.0
Summary: Event detection and transformation for time-series data
Home-page: https://github.com/rwhitt2049/trouve
Author: Ry Whittington
Author-email: rwhitt2049@gmail.com
License: MIT
Keywords: time_series,timeseries,iot,sensor
Classifier: Development Status :: 4 - Beta
Classifier: Intended Audience :: Developers
Classifier: Intended Audience :: Science/Research
Classifier: License :: OSI Approved :: MIT License
Classifier: Operating System :: Microsoft :: Windows
Classifier: Operating System :: POSIX
Classifier: Programming Language :: Python :: 3.3
Classifier: Programming Language :: Python :: 3.4
Classifier: Programming Language :: Python :: 3.5
Classifier: Programming Language :: Python :: 3.6
Classifier: Topic :: Scientific/Engineering
License-File: LICENSE.txt
Requires-Dist: numpy
Requires-Dist: pandas
Requires-Dist: toolz
Provides-Extra: develop
Requires-Dist: pytest ; extra == 'develop'
